tests/__init__.py
tests/test_callbacks.py
tinygrad_lightning/__init__.py
tinygrad_lightning/callback.py
tinygrad_lightning/data.py
tinygrad_lightning/losses.py
tinygrad_lightning/module.py
tinygrad_lightning/trainer.py
tinygrad_lightning/version.py
tinygrad_lightning-0.0.1.dist-info/LICENSE
tinygrad_lightning-0.0.1.dist-info/METADATA
tinygrad_lightning-0.0.1.dist-info/WHEEL
tinygrad_lightning-0.0.1.dist-info/entry_points.txt
tinygrad_lightning-0.0.1.dist-info/top_level.txt
tinygrad_lightning-0.0.1.dist-info/RECORD
