Metadata-Version: 2.1
Name: tinygrad-lightning
Version: 0.0.1
Summary: high level interface for tinygrad
Home-page: https://github.com/baudcode/tinygrad-lightning
Author: Malte Koch
Author-email: malte-koch@gmx.net
Maintainer: Malte Koch
Maintainer-email: malte-koch@gmx.net
License: MIT
Keywords: api,order
Platform: UNKNOWN
Classifier: Development Status :: 3 - Alpha
Classifier: Intended Audience :: Developers
Classifier: Operating System :: POSIX :: Linux
Classifier: Programming Language :: Python :: 3
Requires-Dist: tinygrad
